{"otherData": {},"traceEvents":[{},{"cat":"function","dur":14276,"name":"void __cdecl Reme::RenderCommand::Init(void)","ph":"X","pid":0,"tid":11348,"ts":98811184535.300},{"cat":"function","dur":0,"name":"unsigned int __cdecl Reme::RenderCommand::GetMaxTextureUnit(void)","ph":"X","pid":0,"tid":11348,"ts":98811199005.200},{"cat":"function","dur":12,"name":"class std::shared_ptr<class Reme::VertexArray> __cdecl Reme::VertexArray::Create(void)","ph":"X","pid":0,"tid":11348,"ts":98811210643.900},{"cat":"function","dur":17736,"name":"void __cdecl Reme::Renderer2D::Init(void)","ph":"X","pid":0,"tid":11348,"ts":98811198939.900},{"cat":"function","dur":177,"name":"class std::shared_ptr<class Reme::Texture> __cdecl Reme::Texture::Create(unsigned int,unsigned int)","ph":"X","pid":0,"tid":11348,"ts":98811216741.400},{"cat":"function","dur":76,"name":"class std::shared_ptr<class Reme::Texture> __cdecl Reme::Texture::Create(unsigned int,unsigned int)","ph":"X","pid":0,"tid":11348,"ts":98811217049.400},{"cat":"function","dur":454,"name":"void __cdecl Reme::Texture::Init(void)","ph":"X","pid":0,"tid":11348,"ts":98811216741.300},{"cat":"function","dur":32689,"name":"void __cdecl Reme::Renderer::Init(void)","ph":"X","pid":0,"tid":11348,"ts":98811184535.200},{"cat":"function","dur":446606,"name":"__cdecl Reme::Application::Application(const struct Reme::WindowProps &)","ph":"X","pid":0,"tid":11348,"ts":98810770807.800},{"cat":"function","dur":36942,"name":"class std::shared_ptr<class Reme::Image> __cdecl Reme::Image::Create(const class std::basic_string<char,struct std::char_traits<char>,class std::allocator<char> > &)","ph":"X","pid":0,"tid":11348,"ts":98811217460.900},{"cat":"function","dur":47699,"name":"class std::shared_ptr<class Reme::Texture> __cdecl Reme::Texture::Create(const class std::basic_string<char,struct std::char_traits<char>,class std::allocator<char> > &)","ph":"X","pid":0,"tid":11348,"ts":98811217460.600},{"cat":"function","dur":187918,"name":"class std::shared_ptr<class Reme::Image> __cdecl Reme::Image::Create(const class std::basic_string<char,struct std::char_traits<char>,class std::allocator<char> > &)","ph":"X","pid":0,"tid":11348,"ts":98811265231.300},{"cat":"function","dur":209916,"name":"class std::shared_ptr<class Reme::Texture> __cdecl Reme::Texture::Create(const class std::basic_string<char,struct std::char_traits<char>,class std::allocator<char> > &)","ph":"X","pid":0,"tid":11348,"ts":98811265231.100},{"cat":"function","dur":175455,"name":"class std::shared_ptr<class Reme::Image> __cdecl Reme::Image::Create(const class std::basic_string<char,struct std::char_traits<char>,class std::allocator<char> > &)","ph":"X","pid":0,"tid":11348,"ts":98811475222.800},{"cat":"function","dur":193684,"name":"class std::shared_ptr<class Reme::Texture> __cdecl Reme::Texture::Create(const class std::basic_string<char,struct std::char_traits<char>,class std::allocator<char> > &)","ph":"X","pid":0,"tid":11348,"ts":98811475222.600},{"cat":"function","dur":29832,"name":"class std::shared_ptr<class Reme::Image> __cdecl Reme::Image::Create(const class std::basic_string<char,struct std::char_traits<char>,class std::allocator<char> > &)","ph":"X","pid":0,"tid":11348,"ts":98811668957.500},{"cat":"function","dur":37160,"name":"class std::shared_ptr<class Reme::Texture> __cdecl Reme::Texture::Create(const class std::basic_string<char,struct std::char_traits<char>,class std::allocator<char> > &)","ph":"X","pid":0,"tid":11348,"ts":98811668957.300},{"cat":"function","dur":491056,"name":"void __cdecl Reme::LayerStack::PushLayer(class Reme::Layer *)","ph":"X","pid":0,"tid":11348,"ts":98811217447.200}]}